package com.google.android.m4b.maps.by;

import android.os.Binder;
import android.os.IBinder;
import android.os.IInterface;
import android.os.Parcel;

public abstract interface s
  extends IInterface
{
  public abstract void a(z paramz);
  
  public abstract void d();
  
  public static abstract class a
    extends Binder
    implements s
  {
    public a()
    {
      attachInterface(this, "com.google.android.m4b.maps.internal.ILocationSourceDelegate");
    }
    
    public IBinder asBinder()
    {
      return this;
    }
    
    public boolean onTransact(int paramInt1, Parcel paramParcel1, Parcel paramParcel2, int paramInt2)
    {
      switch (paramInt1)
      {
      default: 
        return super.onTransact(paramInt1, paramParcel1, paramParcel2, paramInt2);
      case 1598968902: 
        paramParcel2.writeString("com.google.android.m4b.maps.internal.ILocationSourceDelegate");
        return true;
      case 1: 
        paramParcel1.enforceInterface("com.google.android.m4b.maps.internal.ILocationSourceDelegate");
        paramParcel1 = paramParcel1.readStrongBinder();
        if (paramParcel1 == null) {
          paramParcel1 = null;
        }
        for (;;)
        {
          a(paramParcel1);
          paramParcel2.writeNoException();
          return true;
          IInterface localIInterface = paramParcel1.queryLocalInterface("com.google.android.m4b.maps.internal.IOnLocationChangeListener");
          if ((localIInterface != null) && ((localIInterface instanceof z))) {
            paramParcel1 = (z)localIInterface;
          } else {
            paramParcel1 = new z.a.a(paramParcel1);
          }
        }
      }
      paramParcel1.enforceInterface("com.google.android.m4b.maps.internal.ILocationSourceDelegate");
      d();
      paramParcel2.writeNoException();
      return true;
    }
    
    static final class a
      implements s
    {
      private IBinder a;
      
      a(IBinder paramIBinder)
      {
        a = paramIBinder;
      }
      
      /* Error */
      public final void a(z paramz)
      {
        // Byte code:
        //   0: invokestatic 25	android/os/Parcel:obtain	()Landroid/os/Parcel;
        //   3: astore_2
        //   4: invokestatic 25	android/os/Parcel:obtain	()Landroid/os/Parcel;
        //   7: astore_3
        //   8: aload_2
        //   9: ldc 27
        //   11: invokevirtual 31	android/os/Parcel:writeInterfaceToken	(Ljava/lang/String;)V
        //   14: aload_1
        //   15: ifnull +42 -> 57
        //   18: aload_1
        //   19: invokeinterface 37 1 0
        //   24: astore_1
        //   25: aload_2
        //   26: aload_1
        //   27: invokevirtual 40	android/os/Parcel:writeStrongBinder	(Landroid/os/IBinder;)V
        //   30: aload_0
        //   31: getfield 17	com/google/android/m4b/maps/by/s$a$a:a	Landroid/os/IBinder;
        //   34: iconst_1
        //   35: aload_2
        //   36: aload_3
        //   37: iconst_0
        //   38: invokeinterface 46 5 0
        //   43: pop
        //   44: aload_3
        //   45: invokevirtual 49	android/os/Parcel:readException	()V
        //   48: aload_3
        //   49: invokevirtual 52	android/os/Parcel:recycle	()V
        //   52: aload_2
        //   53: invokevirtual 52	android/os/Parcel:recycle	()V
        //   56: return
        //   57: aconst_null
        //   58: astore_1
        //   59: goto -34 -> 25
        //   62: astore_1
        //   63: aload_3
        //   64: invokevirtual 52	android/os/Parcel:recycle	()V
        //   67: aload_2
        //   68: invokevirtual 52	android/os/Parcel:recycle	()V
        //   71: aload_1
        //   72: athrow
        // Local variable table:
        //   start	length	slot	name	signature
        //   0	73	0	this	a
        //   0	73	1	paramz	z
        //   3	65	2	localParcel1	Parcel
        //   7	57	3	localParcel2	Parcel
        // Exception table:
        //   from	to	target	type
        //   8	14	62	finally
        //   18	25	62	finally
        //   25	48	62	finally
      }
      
      public final IBinder asBinder()
      {
        return a;
      }
      
      public final void d()
      {
        Parcel localParcel1 = Parcel.obtain();
        Parcel localParcel2 = Parcel.obtain();
        try
        {
          localParcel1.writeInterfaceToken("com.google.android.m4b.maps.internal.ILocationSourceDelegate");
          a.transact(2, localParcel1, localParcel2, 0);
          localParcel2.readException();
          return;
        }
        finally
        {
          localParcel2.recycle();
          localParcel1.recycle();
        }
      }
    }
  }
}

/* Location:
 * Qualified Name:     com.google.android.m4b.maps.by.s
 * Java Class Version: 6 (50.0)
 * JD-Core Version:    0.7.1
 */