package com.google.android.m4b.maps.bq;

import java.util.List;

final class bm$1
  extends Thread
{
  bm$1(bm parambm, List paramList) {}
  
  /* Error */
  public final void run()
  {
    // Byte code:
    //   0: new 28	java/lang/StringBuilder
    //   3: dup
    //   4: ldc 30
    //   6: invokespecial 33	java/lang/StringBuilder:<init>	(Ljava/lang/String;)V
    //   9: astore_2
    //   10: aload_2
    //   11: ldc 35
    //   13: invokevirtual 39	java/lang/StringBuilder:append	(Ljava/lang/String;)Ljava/lang/StringBuilder;
    //   16: pop
    //   17: aload_2
    //   18: ldc 41
    //   20: invokevirtual 39	java/lang/StringBuilder:append	(Ljava/lang/String;)Ljava/lang/StringBuilder;
    //   23: pop
    //   24: aload_2
    //   25: ldc 43
    //   27: invokevirtual 39	java/lang/StringBuilder:append	(Ljava/lang/String;)Ljava/lang/StringBuilder;
    //   30: pop
    //   31: aload_2
    //   32: iconst_3
    //   33: invokevirtual 46	java/lang/StringBuilder:append	(I)Ljava/lang/StringBuilder;
    //   36: pop
    //   37: aload_2
    //   38: ldc 48
    //   40: invokevirtual 39	java/lang/StringBuilder:append	(Ljava/lang/String;)Ljava/lang/StringBuilder;
    //   43: pop
    //   44: aload_2
    //   45: aload_0
    //   46: getfield 16	com/google/android/m4b/maps/bq/bm$1:b	Lcom/google/android/m4b/maps/bq/bm;
    //   49: invokestatic 51	com/google/android/m4b/maps/bq/bm:a	(Lcom/google/android/m4b/maps/bq/bm;)Ljava/lang/String;
    //   52: invokevirtual 39	java/lang/StringBuilder:append	(Ljava/lang/String;)Ljava/lang/StringBuilder;
    //   55: pop
    //   56: aload_0
    //   57: getfield 18	com/google/android/m4b/maps/bq/bm$1:a	Ljava/util/List;
    //   60: invokeinterface 57 1 0
    //   65: astore_3
    //   66: ldc 59
    //   68: astore_1
    //   69: aload_3
    //   70: invokeinterface 65 1 0
    //   75: ifeq +53 -> 128
    //   78: aload_3
    //   79: invokeinterface 69 1 0
    //   84: checkcast 71	com/google/android/m4b/maps/bq/bl$a
    //   87: astore 4
    //   89: aload_2
    //   90: aload_1
    //   91: invokevirtual 39	java/lang/StringBuilder:append	(Ljava/lang/String;)Ljava/lang/StringBuilder;
    //   94: pop
    //   95: aload_2
    //   96: aload 4
    //   98: getfield 74	com/google/android/m4b/maps/bq/bl$a:a	Ljava/lang/String;
    //   101: invokevirtual 39	java/lang/StringBuilder:append	(Ljava/lang/String;)Ljava/lang/StringBuilder;
    //   104: pop
    //   105: aload_2
    //   106: ldc 76
    //   108: invokevirtual 39	java/lang/StringBuilder:append	(Ljava/lang/String;)Ljava/lang/StringBuilder;
    //   111: pop
    //   112: aload_2
    //   113: aload 4
    //   115: invokevirtual 79	com/google/android/m4b/maps/bq/bl$a:a	()J
    //   118: invokevirtual 82	java/lang/StringBuilder:append	(J)Ljava/lang/StringBuilder;
    //   121: pop
    //   122: ldc 84
    //   124: astore_1
    //   125: goto -56 -> 69
    //   128: aload_0
    //   129: getfield 18	com/google/android/m4b/maps/bq/bm$1:a	Ljava/util/List;
    //   132: invokeinterface 57 1 0
    //   137: astore_3
    //   138: ldc 86
    //   140: astore_1
    //   141: aload_3
    //   142: invokeinterface 65 1 0
    //   147: ifeq +44 -> 191
    //   150: aload_3
    //   151: invokeinterface 69 1 0
    //   156: checkcast 71	com/google/android/m4b/maps/bq/bl$a
    //   159: astore 4
    //   161: aload_2
    //   162: aload_1
    //   163: invokevirtual 39	java/lang/StringBuilder:append	(Ljava/lang/String;)Ljava/lang/StringBuilder;
    //   166: pop
    //   167: aload_2
    //   168: aload 4
    //   170: getfield 90	com/google/android/m4b/maps/bq/bl$a:c	J
    //   173: aload_0
    //   174: getfield 16	com/google/android/m4b/maps/bq/bm$1:b	Lcom/google/android/m4b/maps/bq/bm;
    //   177: invokestatic 93	com/google/android/m4b/maps/bq/bm:b	(Lcom/google/android/m4b/maps/bq/bm;)J
    //   180: lsub
    //   181: invokevirtual 82	java/lang/StringBuilder:append	(J)Ljava/lang/StringBuilder;
    //   184: pop
    //   185: ldc 84
    //   187: astore_1
    //   188: goto -47 -> 141
    //   191: new 95	java/net/URL
    //   194: dup
    //   195: aload_2
    //   196: invokevirtual 99	java/lang/StringBuilder:toString	()Ljava/lang/String;
    //   199: invokespecial 100	java/net/URL:<init>	(Ljava/lang/String;)V
    //   202: astore_1
    //   203: aconst_null
    //   204: astore_2
    //   205: aload_1
    //   206: invokevirtual 104	java/net/URL:openConnection	()Ljava/net/URLConnection;
    //   209: checkcast 106	java/net/HttpURLConnection
    //   212: astore_1
    //   213: aload_1
    //   214: ldc 108
    //   216: ldc 110
    //   218: invokestatic 116	java/lang/System:getProperty	(Ljava/lang/String;)Ljava/lang/String;
    //   221: invokevirtual 120	java/net/HttpURLConnection:setRequestProperty	(Ljava/lang/String;Ljava/lang/String;)V
    //   224: aload_1
    //   225: invokevirtual 124	java/net/HttpURLConnection:getResponseCode	()I
    //   228: pop
    //   229: aload_1
    //   230: ifnull +7 -> 237
    //   233: aload_1
    //   234: invokevirtual 127	java/net/HttpURLConnection:disconnect	()V
    //   237: return
    //   238: astore_1
    //   239: aconst_null
    //   240: astore_1
    //   241: aload_1
    //   242: ifnull -5 -> 237
    //   245: aload_1
    //   246: invokevirtual 127	java/net/HttpURLConnection:disconnect	()V
    //   249: return
    //   250: astore_3
    //   251: aload_2
    //   252: astore_1
    //   253: aload_3
    //   254: astore_2
    //   255: aload_1
    //   256: ifnull +7 -> 263
    //   259: aload_1
    //   260: invokevirtual 127	java/net/HttpURLConnection:disconnect	()V
    //   263: aload_2
    //   264: athrow
    //   265: astore_2
    //   266: goto -11 -> 255
    //   269: astore_2
    //   270: goto -29 -> 241
    //   273: astore_1
    //   274: return
    // Local variable table:
    //   start	length	slot	name	signature
    //   0	275	0	this	1
    //   68	166	1	localObject1	Object
    //   238	1	1	localIOException1	java.io.IOException
    //   240	20	1	localObject2	Object
    //   273	1	1	localMalformedURLException	java.net.MalformedURLException
    //   9	255	2	localObject3	Object
    //   265	1	2	localObject4	Object
    //   269	1	2	localIOException2	java.io.IOException
    //   65	86	3	localIterator	java.util.Iterator
    //   250	4	3	localObject5	Object
    //   87	82	4	locala	bl.a
    // Exception table:
    //   from	to	target	type
    //   205	213	238	java/io/IOException
    //   205	213	250	finally
    //   213	229	265	finally
    //   213	229	269	java/io/IOException
    //   191	203	273	java/net/MalformedURLException
  }
}

/* Location:
 * Qualified Name:     com.google.android.m4b.maps.bq.bm.1
 * Java Class Version: 6 (50.0)
 * JD-Core Version:    0.7.1
 */